{
  "frames": {
    "attack1_001": {
      "x": 0,
      "y": 0,
      "w": 273,
      "h": 266
    },
    "attack1_002": {
      "x": 273,
      "y": 0,
      "w": 273,
      "h": 266
    },
    "attack1_003": {
      "x": 546,
      "y": 0,
      "w": 273,
      "h": 266
    },
    "attack1_004": {
      "x": 819,
      "y": 0,
      "w": 273,
      "h": 266
    },
    "attack1_005": {
      "x": 1092,
      "y": 0,
      "w": 273,
      "h": 266
    },
    "attack1_006": {
      "x": 0,
      "y": 266,
      "w": 273,
      "h": 266
    },
    "attack1_007": {
      "x": 273,
      "y": 266,
      "w": 273,
      "h": 266
    },
    "attack1_008": {
      "x": 546,
      "y": 266,
      "w": 273,
      "h": 266
    },
    "attack1_009": {
      "x": 819,
      "y": 266,
      "w": 273,
      "h": 266
    },
    "attack1_010": {
      "x": 1092,
      "y": 266,
      "w": 273,
      "h": 266
    },
    "attack1_011": {
      "x": 0,
      "y": 532,
      "w": 273,
      "h": 266
    },
    "attack1_012": {
      "x": 273,
      "y": 532,
      "w": 273,
      "h": 266
    },
    "attack1_013": {
      "x": 546,
      "y": 532,
      "w": 273,
      "h": 266
    },
    "attack1_014": {
      "x": 819,
      "y": 532,
      "w": 273,
      "h": 266
    },
    "attack1_015": {
      "x": 1092,
      "y": 532,
      "w": 273,
      "h": 266
    },
    "attack1_016": {
      "x": 0,
      "y": 798,
      "w": 273,
      "h": 266
    },
    "attack1_017": {
      "x": 273,
      "y": 798,
      "w": 273,
      "h": 266
    },
    "attack1_018": {
      "x": 546,
      "y": 798,
      "w": 273,
      "h": 266
    },
    "attack1_019": {
      "x": 819,
      "y": 798,
      "w": 273,
      "h": 266
    },
    "attack1_020": {
      "x": 1092,
      "y": 798,
      "w": 273,
      "h": 266
    },
    "attack1_021": {
      "x": 0,
      "y": 1064,
      "w": 273,
      "h": 266
    },
    "attack1_022": {
      "x": 273,
      "y": 1064,
      "w": 273,
      "h": 266
    },
    "attack1_023": {
      "x": 546,
      "y": 1064,
      "w": 273,
      "h": 266
    }
  },
  "meta": {
    "image": "sprite.png",
    "size": {
      "w": 1365,
      "h": 1330
    },
    "frameSize": {
      "w": 273,
      "h": 266
    },
    "columns": 5,
    "rows": 5,
    "frameCount": 23
  }
}