{
  "frames": {
    "idle_001": {
      "x": 0,
      "y": 0,
      "w": 82,
      "h": 83
    },
    "idle_002": {
      "x": 82,
      "y": 0,
      "w": 82,
      "h": 83
    },
    "idle_003": {
      "x": 164,
      "y": 0,
      "w": 82,
      "h": 83
    },
    "idle_004": {
      "x": 246,
      "y": 0,
      "w": 82,
      "h": 83
    },
    "idle_005": {
      "x": 328,
      "y": 0,
      "w": 82,
      "h": 83
    },
    "idle_006": {
      "x": 0,
      "y": 83,
      "w": 82,
      "h": 83
    },
    "idle_007": {
      "x": 82,
      "y": 83,
      "w": 82,
      "h": 83
    },
    "idle_008": {
      "x": 164,
      "y": 83,
      "w": 82,
      "h": 83
    },
    "idle_009": {
      "x": 246,
      "y": 83,
      "w": 82,
      "h": 83
    },
    "idle_010": {
      "x": 328,
      "y": 83,
      "w": 82,
      "h": 83
    },
    "idle_011": {
      "x": 0,
      "y": 166,
      "w": 82,
      "h": 83
    },
    "idle_012": {
      "x": 82,
      "y": 166,
      "w": 82,
      "h": 83
    },
    "idle_013": {
      "x": 164,
      "y": 166,
      "w": 82,
      "h": 83
    },
    "idle_014": {
      "x": 246,
      "y": 166,
      "w": 82,
      "h": 83
    },
    "idle_015": {
      "x": 328,
      "y": 166,
      "w": 82,
      "h": 83
    },
    "idle_016": {
      "x": 0,
      "y": 249,
      "w": 82,
      "h": 83
    },
    "idle_017": {
      "x": 82,
      "y": 249,
      "w": 82,
      "h": 83
    },
    "idle_018": {
      "x": 164,
      "y": 249,
      "w": 82,
      "h": 83
    },
    "idle_019": {
      "x": 246,
      "y": 249,
      "w": 82,
      "h": 83
    },
    "idle_020": {
      "x": 328,
      "y": 249,
      "w": 82,
      "h": 83
    }
  },
  "meta": {
    "image": "sprite.png",
    "size": {
      "w": 410,
      "h": 332
    },
    "frameSize": {
      "w": 82,
      "h": 83
    },
    "columns": 5,
    "rows": 4,
    "frameCount": 20
  }
}